exponential_backoff_ca/__init__.py
exponential_backoff_ca/py.typed
exponential_backoff_ca-2.4.dist-info/METADATA
exponential_backoff_ca-2.4.dist-info/WHEEL
exponential_backoff_ca-2.4.dist-info/top_level.txt
exponential_backoff_ca-2.4.dist-info/RECORD
