Metadata-Version: 2.1
Name: exponential_backoff_ca
Version: 2.4
Summary: An exponential backoff iterator with collision avoidance.
Author: IEDO Team
Project-URL: Repository, https://github.com/macrotex/python-exponential-backoff-ca
Classifier: Development Status :: 3 - Alpha
Classifier: License :: OSI Approved :: MIT License
Requires-Python: >=3.9
